vellum/__init__.py
vellum/client.py
vellum/core/__init__.py
vellum/core/api_error.py
vellum/core/datetime_utils.py
vellum/core/jsonable_encoder.py
vellum/core/remove_none_from_headers.py
vellum/environment.py
vellum/py.typed
vellum/resources/__init__.py
vellum/resources/documents/__init__.py
vellum/resources/documents/client.py
vellum/resources/model_versions/__init__.py
vellum/resources/model_versions/client.py
vellum/types/__init__.py
vellum/types/document.py
vellum/types/document_document_to_document_index.py
vellum/types/enriched_normalized_completion.py
vellum/types/finish_reason_enum.py
vellum/types/generate_error_response.py
vellum/types/generate_options_request.py
vellum/types/generate_request_request.py
vellum/types/generate_response.py
vellum/types/generate_result.py
vellum/types/generate_result_data.py
vellum/types/generate_result_error.py
vellum/types/indexing_state_enum.py
vellum/types/logprobs_enum.py
vellum/types/model_type_enum.py
vellum/types/model_version_build_config.py
vellum/types/model_version_exec_config_parameters.py
vellum/types/model_version_exec_config_read.py
vellum/types/model_version_read.py
vellum/types/model_version_sandbox_snapshot.py
vellum/types/normalized_log_probs.py
vellum/types/normalized_token_log_probs.py
vellum/types/paginated_slim_document_list.py
vellum/types/processing_state_enum.py
vellum/types/provider_enum.py
vellum/types/search_error_response.py
vellum/types/search_filters_request.py
vellum/types/search_request_options_request.py
vellum/types/search_response.py
vellum/types/search_result.py
vellum/types/search_result_merging_request.py
vellum/types/search_weights_request.py
vellum/types/slim_document.py
vellum/types/status_enum.py
vellum/types/submit_completion_actual_request.py
vellum/types/submit_completion_actuals_error_response.py
vellum/types/upload_document_error_response.py
vellum/types/upload_document_response.py
vellumdev-0.0.20.dist-info/METADATA
vellumdev-0.0.20.dist-info/WHEEL
vellumdev-0.0.20.dist-info/RECORD
